agentflare_sdk/__init__.py
agentflare_sdk/skeleton.py
agentflare_sdk-0.0.0.dist-info/licenses/LICENSE.txt
agentflare_sdk-0.0.0.dist-info/METADATA
agentflare_sdk-0.0.0.dist-info/WHEEL
agentflare_sdk-0.0.0.dist-info/top_level.txt
agentflare_sdk-0.0.0.dist-info/RECORD
